{
    "lavender-purple": {
        "50": "#f3e7fe",
        "100": "#e6cefd",
        "200": "#ce9efa",
        "300": "#b56df8",
        "400": "#9c3cf6",
        "500": "#830bf4",
        "600": "#6909c3",
        "700": "#4f0792",
        "800": "#350561",
        "900": "#1a0231",
        "950": "#120222"
    },
    "bright-lavender": {
        "50": "#f2e6fe",
        "100": "#e5cdfe",
        "200": "#cc9cfc",
        "300": "#b26afb",
        "400": "#9938fa",
        "500": "#7f06f9",
        "600": "#6605c7",
        "700": "#4c0495",
        "800": "#330363",
        "900": "#190132",
        "950": "#120123"
    },
    "space-indigo": {
        "50": "#edecf8",
        "100": "#dbdaf1",
        "200": "#b7b4e4",
        "300": "#938fd6",
        "400": "#6f69c9",
        "500": "#4c44bb",
        "600": "#3c3696",
        "700": "#2d2970",
        "800": "#1e1b4b",
        "900": "#0f0e25",
        "950": "#0b091a"
    },
    "prussian-blue": {
        "50": "#ecf0f8",
        "100": "#dae1f1",
        "200": "#b4c2e4",
        "300": "#8fa4d6",
        "400": "#6986c9",
        "500": "#4468bb",
        "600": "#365396",
        "700": "#293e70",
        "800": "#1b294b",
        "900": "#0e1525",
        "950": "#090e1a"
    },
    "deep-space-blue": {
        "50": "#eef1f6",
        "100": "#dde4ee",
        "200": "#bbc8dd",
        "300": "#99adcc",
        "400": "#7791bb",
        "500": "#5576aa",
        "600": "#445e88",
        "700": "#334766",
        "800": "#222f44",
        "900": "#111822",
        "950": "#0c1018"
    }
}